README.md
setup.cfg
setup.py
instaclient/__init__.py
instaclient.egg-info/PKG-INFO
instaclient.egg-info/SOURCES.txt
instaclient.egg-info/dependency_links.txt
instaclient.egg-info/requires.txt
instaclient.egg-info/top_level.txt
instaclient/client/__init__.py
instaclient/client/auth.py
instaclient/client/checker.py
instaclient/client/component.py
instaclient/client/constants.py
instaclient/client/driver.py
instaclient/client/instaclient.py
instaclient/client/interactions.py
instaclient/client/navigator.py
instaclient/client/scraper.py
instaclient/errors/__init__.py
instaclient/errors/common.py
instaclient/errors/navigator.py
instaclient/instagram/__init__.py
instaclient/instagram/address.py
instaclient/instagram/comment.py
instaclient/instagram/hashtag.py
instaclient/instagram/instaobject.py
instaclient/instagram/location.py
instaclient/instagram/notification.py
instaclient/instagram/post.py
instaclient/instagram/postmedia.py
instaclient/instagram/profile.py
tests/__init__.py
tests/tests.py