Metadata-Version: 2.1
Name: instaclient
Version: 2.9.12
Summary: Instagram client built with Python 3.8 and the Selenium package.
Home-page: https://github.com/davidwickerhf/instaclient
Author: David Wicker
Author-email: davidwickerhf@gmail.com
License: MIT
Download-URL: https://github.com/davidwickerhf/instaclient/archive/v2.9.12.tar.gz
Keywords: INSTAGRAM,BOT,INSTAGRAM BOT,INSTAGRAM CLIENT
Platform: UNKNOWN
Classifier: Development Status :: 5 - Production/Stable
Classifier: Intended Audience :: Developers
Classifier: Topic :: Software Development :: Build Tools
Classifier: License :: OSI Approved :: MIT License
Classifier: Programming Language :: Python :: 3.7
Classifier: Programming Language :: Python :: 3.8
Classifier: Programming Language :: Python :: 3.9
